ts_ensourcel/__init__.py
ts_ensourcel/types.py
ts_ensourcel/utils.py
ts_ensourcel/transliterate/__init__.py
ts_ensourcel-0.2.5.dist-info/METADATA
ts_ensourcel-0.2.5.dist-info/WHEEL
ts_ensourcel-0.2.5.dist-info/entry_points.txt
ts_ensourcel-0.2.5.dist-info/RECORD
