Metadata-Version: 2.4
Name: ts-ensourcel
Version: 0.2.5
Summary: Project about creating a canonical digital taittiriya samhita text representation
Requires-Python: >=3.12
Requires-Dist: aksharamukha>=2.3
Requires-Dist: bs4>=0.0.2
Requires-Dist: requests>=2.32.3
